event_study_toolkit/__init__.py
event_study_toolkit/data_panel.csv
event_study_toolkit/event_panel.csv
event_study_toolkit/eventstudy.py
event_study_toolkit-1.0.0.dist-info/LICENSE
event_study_toolkit-1.0.0.dist-info/METADATA
event_study_toolkit-1.0.0.dist-info/WHEEL
event_study_toolkit-1.0.0.dist-info/top_level.txt
event_study_toolkit-1.0.0.dist-info/RECORD
