Metadata-Version: 2.1
Name: event-study-toolkit
Version: 1.0.0
Summary: A package for conducting event studies
Author: researchrebel
Author-email: amoossavi21@gmail.com
Classifier: Programming Language :: Python :: 3
Classifier: License :: OSI Approved :: MIT License
Classifier: Operating System :: OS Independent
Requires-Python: >=3.7
License-File: LICENSE
Requires-Dist: pandas
Requires-Dist: numpy
Requires-Dist: statsmodels
Requires-Dist: scipy
Requires-Dist: pandas-market-calendars
Requires-Dist: scikit-learn
